logix/__init__.py
logix/batch_info.py
logix/config.py
logix/constants.py
logix/logix.py
logix/scheduler.py
logix/state.py
logix/utils.py
logix/analysis/__init__.py
logix/analysis/influence_function.py
logix/analysis/influence_function_utils.py
logix/huggingface/__init__.py
logix/huggingface/arguments.py
logix/huggingface/callback.py
logix/huggingface/patch.py
logix/lightning/__init__.py
logix/lightning/arguments.py
logix/lightning/callback.py
logix/lightning/patch.py
logix/logging/__init__.py
logix/logging/log_loader.py
logix/logging/log_loader_utils.py
logix/logging/log_saver.py
logix/logging/logger.py
logix/logging/mmap.py
logix/logging/option.py
logix/logging/utils.py
logix/lora/__init__.py
logix/lora/lora.py
logix/lora/modules.py
logix/lora/utils.py
logix/statistic/__init__.py
logix/statistic/corrected_eigval.py
logix/statistic/covariance.py
logix/statistic/log.py
logix/statistic/mean.py
logix/statistic/utils.py
logix/statistic/variance.py
logix_ai-0.1.1.dist-info/LICENSE
logix_ai-0.1.1.dist-info/METADATA
logix_ai-0.1.1.dist-info/WHEEL
logix_ai-0.1.1.dist-info/top_level.txt
logix_ai-0.1.1.dist-info/RECORD
